bugbug/__init__.py
bugbug/bug_features.py
bugbug/bug_snapshot.py
bugbug/bugzilla.py
bugbug/commit_features.py
bugbug/db.py
bugbug/feature_cleanup.py
bugbug/github.py
bugbug/issue_features.py
bugbug/issue_snapshot.py
bugbug/labels.py
bugbug/model.py
bugbug/model_calibration.py
bugbug/nlp.py
bugbug/phabricator.py
bugbug/repository.py
bugbug/rust_code_analysis_server.py
bugbug/swarm.py
bugbug/test_scheduling.py
bugbug/test_scheduling_features.py
bugbug/utils.py
bugbug/vectordb.py
bugbug/code_search/__init__.py
bugbug/code_search/function_search.py
bugbug/code_search/mozilla.py
bugbug/code_search/parser.py
bugbug/code_search/searchfox_api.py
bugbug/code_search/searchfox_data.py
bugbug/code_search/searchfox_download.py
bugbug/labels/annotateignore.csv
bugbug/labels/bug_nobug.csv
bugbug/labels/defect_enhancement_task.csv
bugbug/labels/defect_enhancement_task_e.csv
bugbug/labels/defect_enhancement_task_h.csv
bugbug/labels/defect_enhancement_task_p.csv
bugbug/labels/defect_enhancement_task_s.csv
bugbug/labels/regression_bug_nobug.csv
bugbug/labels/regressionrange.csv
bugbug/labels/str.csv
bugbug/labels/tracking.csv
bugbug/models/__init__.py
bugbug/models/accessibility.py
bugbug/models/annotate_ignore.py
bugbug/models/assignee.py
bugbug/models/backout.py
bugbug/models/browsername.py
bugbug/models/bugtype.py
bugbug/models/component.py
bugbug/models/defect.py
bugbug/models/defect_enhancement_task.py
bugbug/models/devdocneeded.py
bugbug/models/fenixcomponent.py
bugbug/models/fixtime.py
bugbug/models/invalid_compatibility_report.py
bugbug/models/needsdiagnosis.py
bugbug/models/performancebug.py
bugbug/models/qaneeded.py
bugbug/models/rcatype.py
bugbug/models/regression.py
bugbug/models/regressionrange.py
bugbug/models/regressor.py
bugbug/models/spambug.py
bugbug/models/stepstoreproduce.py
bugbug/models/testfailure.py
bugbug/models/testselect.py
bugbug/models/tracking.py
bugbug/models/uplift.py
bugbug/models/worksforme.py
bugbug/tools/__init__.py
bugbug/tools/base.py
bugbug-0.0.617.dist-info/LICENSE
bugbug-0.0.617.dist-info/METADATA
bugbug-0.0.617.dist-info/WHEEL
bugbug-0.0.617.dist-info/entry_points.txt
bugbug-0.0.617.dist-info/top_level.txt
bugbug-0.0.617.dist-info/RECORD
