Metadata-Version: 2.1
Name: bugbug
Version: 0.0.617
Summary: ML tools for Mozilla projects
Author: Marco Castelluccio
Author-email: mcastelluccio@mozilla.com
License: MPL2
Classifier: Programming Language :: Python :: 3.10
Classifier: Programming Language :: Python :: 3.9
Classifier: Programming Language :: Python :: 3 :: Only
Classifier: License :: OSI Approved :: Mozilla Public License 2.0 (MPL 2.0)
License-File: LICENSE
Requires-Dist: amqp ==5.3.1
Requires-Dist: beautifulsoup4 ==4.14.3
Requires-Dist: boto3 ==1.41.2
Requires-Dist: imbalanced-learn ==0.14.0
Requires-Dist: langchain-anthropic ==1.3.0
Requires-Dist: langchain-classic ==1.0.0
Requires-Dist: langchain-community ==0.4.1
Requires-Dist: langchain-google-genai ==4.1.2
Requires-Dist: langchain-mistralai ==1.0.1
Requires-Dist: langchain-openai ==1.1.6
Requires-Dist: langchain ==1.2.0
Requires-Dist: langgraph ==1.0.5
Requires-Dist: libmozdata ==0.2.12
Requires-Dist: llama-cpp-python ==0.2.90
Requires-Dist: lmdb ==1.7.5
Requires-Dist: lxml-html-clean ==0.4.3
Requires-Dist: markdown2 ==2.5.4
Requires-Dist: matplotlib ==3.10.7
Requires-Dist: mercurial ==7.1.2
Requires-Dist: microannotate ==0.0.24
Requires-Dist: mozci ==2.4.3
Requires-Dist: numpy ==2.3.5
Requires-Dist: orjson ==3.11.5
Requires-Dist: ortools ==9.14.6206
Requires-Dist: pandas ==2.3.3
Requires-Dist: psutil ==7.1.3
Requires-Dist: pyOpenSSL >=0.14
Requires-Dist: python-dateutil ==2.9.0.post0
Requires-Dist: python-hglib ==2.6.2
Requires-Dist: qdrant-client ==1.15.1
Requires-Dist: ratelimit ==2.2.1
Requires-Dist: requests-html ==0.10.0
Requires-Dist: requests ==2.32.5
Requires-Dist: rs-parsepatch ==0.4.4
Requires-Dist: scikit-learn ==1.7.2
Requires-Dist: scipy ==1.16.3
Requires-Dist: sendgrid ==6.12.5
Requires-Dist: shap[plots] ==0.50.0
Requires-Dist: tabulate ==0.9.0
Requires-Dist: taskcluster ==94.1.1
Requires-Dist: tenacity ==9.1.2
Requires-Dist: tqdm ==4.67.1
Requires-Dist: unidiff ==0.7.5
Requires-Dist: xgboost ==3.1.2
Requires-Dist: zstandard ==0.25.0
Provides-Extra: nlp
Requires-Dist: gensim ==4.4.0 ; extra == 'nlp'
Requires-Dist: spacy ==3.8.11 ; extra == 'nlp'
Provides-Extra: nn
